{
  "data": {
    "stage": {
      "shape": [
        {
          "name": "MovieClip",
          "text": "toDo",
          "x": "511.75",
          "y": "437.1",
          "level": "19",
          "Angle": "0"
        },
       
        
        {
          "name": "Lamp",
          "text": "toDo",
          "x": "255.95",
          "y": "18.85",
          "level": "19",
          "Enabled": "true",
          "Activate": "k",
          "Angle": "0"
        },
        {
          "name": "GreenButton",
          "text": "toDo",
          "x": "164.75",
          "y": "34.5",
          "level": "19",
          "Angle": "180",
          "Switch": "k2"
        },
        {
          "name": "BlueButton",
          "text": "toDo",
          "x": "23.35",
          "y": "151.2",
          "level": "19",
          "Angle": "90",
          "Switch": "k1"
        },
        {
          "name": "Elevator",
          "text": "toDo",
          "x": "308.65",
          "y": "341.7",
          "level": "19",
          "Enabled": "false",
          "Activate": "k2",
          "ChangeDirection": "k2",
          "AutoChange": "false",
          "End": "0",
          "EndPoint": "end2",
          "Speed": "1",
          "Try": "0",
          "Start": "0",
          "StopTime": "2000"
        },
        {
          "name": "Elevator",
          "text": "toDo",
          "x": "105.05",
          "y": "205.2",
          "level": "19",
          "Enabled": "false",
          "Activate": "k1",
          "ChangeDirection": "k1",
          "AutoChange": "false",
          "End": "0",
          "EndPoint": "end1",
          "Speed": "2",
          "Try": "0",
          "Start": "0",
          "StopTime": "0"
        },
        {
          "name": "SquareBox1",
          "text": "toDo",
          "x": "629.7",
          "y": "102.1",
          "level": "19",
          "alpha": "0.6015625"
        },
        {
          "name": "SquareBox1",
          "text": "toDo",
          "x": "192.65",
          "y": "160.8",
          "level": "19",
          "alpha": "1"
        },
        {
          "name": "TruckLoader",
          "text": "toDo",
          "x": "609.15",
          "y": "382.7",
          "level": "19",
          "truckPoints": "-37,26:-40.5,-10:-11,-24:11,-24:40.5,-10:37,26:609.15,382.7:585.65,405.7:632.65,405.7:609.6999999999999,352.8:609.15,368.45:609.55,370.5:609.6999999999999,317.6:609.1,334.4:609.25,282.4:609.4,294.5:"
        },
        {
          "name": "Shape",
          "text": "toDo",
          "x": "0",
          "y": "0",
          "Angle": "\"0\"",
          "level": "19"
        },
        {
          "name": "LeaveTheTruck",
          "text": "toDo",
          "x": "440.15",
          "y": "78.7",
          "level": "19",
          "Angle": "\"0\""
        },
        {
          "name": "Truck",
          "text": "toDo",
          "x": "618.55",
          "y": "111.75",
          "level": "19",
          "truckPoints": "-135,50:-135,12:36,12:140,12:140,50:36,12:36,-66:117,-66:140,-20:140,12:688.55,167.75:540.55,167.75:"
        },
        {
          "name": "MovieClip",
          "text": "toDo",
          "x": "499.15",
          "y": "52.65",
          "level": "19",
          "Angle": "0"
        },
        {
          "name": "StaticText",
          "text":"warning",
          "x": "63.65",
          "y": "134.65",
          "level": "19",
          "Angle": "\"0\""
        },
        {
          "name": "Shape",
          "text": "toDo",
          "x": "0",
          "y": "0",
          "Angle": "\"0\"",
          "level": "19"
        },
        {
          "name": "ElevatorEnd",
          "text": "toDo",
          "x": "307.65",
          "y": "164.9",
          "level": "19",
          "ename": "end2"
        },
        {
          "name": "ElevatorEnd",
          "text": "toDo",
          "x": "104.05",
          "y": "394",
          "level": "19",
          "ename": "end1"
        },
		{
          "name": "MovieClip",
          "text": "elevLine4",
          "x": "23",
          "y": "194",
          "level": "19",
          "Angle": "0"
        },
		  {
          "name": "MovieClip",
          "text": "elevLine6",
          "x": "226",
          "y": "154",
          "level": "15",
          "Angle": "180"
        },
		 {
          "name": "HalfShadow",
          "text": "toDo",
          "x": "310",
          "y": "302",
          "level": "19",
          "Switch": "undefined",
          "WidthHeight": "75.7 315.85",
          "Angle": "-90"
        },
        {
          "name": "HalfShadow",
          "text": "toDo",
          "x": "39.05",
          "y": "350",
          "level": "19",
          "Switch": "undefined",
          "WidthHeight": "110.2 190",
          "Angle": "-90"
        },
        {
          "name": "HalfShadow",
          "text": "toDo",
          "x": "440",
          "y": "240",
          "level": "19",
          "Switch": "undefined",
          "WidthHeight": "240 220",
          "Angle": "180"
        },
        {
          "name": "StaticText",
          "text": "LEVEL 19
Black Mesa",
          "x": "207.9",
          "y": "54.65",
          "level": "19",
          "Angle": "\"0\""
        },
        {
          "name": "verts",
          "xy1": "-261.1464295211216,132.01495693486095 : -286.0683045211216,117.01495693486095 : -286.0683045211216,72.01495693486095 : -283.6073670211216,69.55401943486095 : -263.6073670211216,82.60089443486095 : -261.1464295211216,87.01495693486095 :",
          "xy2": "211.4609375,435.95 : 186.5390625,420.95 : 186.5390625,375.95 : 189,373.4890625 : 209,386.5359375 : 211.4609375,390.95 :"
        },
        {
          "name": "verts",
          "xy1": "-258.6073670211216,136.58526943486095 : -304.0370545211216,147.01495693486095 : -286.0683045211216,117.01495693486095 : -261.1464295211216,132.01495693486095 :",
          "xy2": "214,440.5203125 : 168.5703125,450.95 : 186.5390625,420.95 : 211.4609375,435.95 :"
        },
        {
          "name": "verts",
          "xy1": "-289.1151795211216,162.01495693486095 : -182.0839295211216,192.01495693486095 : -183.6073670211216,196.58526943486095 : -278.6073670211216,196.58526943486095 :",
          "xy2": "183.4921875,465.95 : 290.5234375,495.95 : 289,500.5203125 : 194,500.5203125 :"
        },
        {
          "name": "verts",
          "xy1": "-289.1151795211216,162.01495693486095 : -305.1308045211216,152.01495693486095 : -304.0370545211216,147.01495693486095 : -258.6073670211216,136.58526943486095 : -233.6073670211216,136.58526943486095 : -183.6073670211216,189.55401943486095 : -182.0839295211216,192.01495693486095 :",
          "xy2": "183.4921875,465.95 : 167.4765625,455.95 : 168.5703125,450.95 : 214,440.5203125 : 239,440.5203125 : 289,493.4890625 : 290.5234375,495.95 :"
        },
        {
          "name": "verts",
          "xy1": "-261.1464295211216,-67.98504306513905 : -263.6073670211216,-65.36785556513905 : -283.6073670211216,-53.41473056513905 : -286.0683045211216,-57.98504306513905 : -286.0683045211216,-117.98504306513905 : -283.6073670211216,-121.38348056513905 : -263.6073670211216,-121.38348056513905 : -261.1464295211216,-117.98504306513905 :",
          "xy2": "211.4609375,235.95 : 209,238.5671875 : 189,250.5203125 : 186.5390625,245.95 : 186.5390625,185.95 : 189,182.5515625 : 209,182.5515625 : 211.4609375,185.95 :"
        },
        {
          "name": "verts",
          "xy1": "556.3926329788784,-75.36785556513905 : 231.3926329788784,-75.36785556513905 : 560.4606017288783,-77.98504306513905 :",
          "xy2": "1029,228.5671875 : 704,228.5671875 : 1033.0679687499999,225.95 :"
        },
        {
          "name": "verts",
          "xy1": "59.947320478878396,117.01495693486095 : -21.146429521121604,117.01495693486095 : -36.068304521121604,87.01495693486095 : -36.068304521121604,62.01495693486095 : -33.607367021121604,60.64776943486095 : -3.607367021121604,69.55401943486095 : 31.978570478878396,82.01495693486095 :",
          "xy2": "532.5546875,420.95 : 451.4609375,420.95 : 436.5390625,390.95 : 436.5390625,365.95 : 439,364.5828125 : 469,373.4890625 : 504.5859375,385.95 :"
        },
        {
          "name": "verts",
          "xy1": "86.3926329788784,118.61651943486095 : 131.3926329788784,142.60089443486095 : -3.607367021121604,147.60089443486095 : -21.146429521121604,117.01495693486095 : 59.947320478878396,117.01495693486095 :",
          "xy2": "559,422.5515625 : 604,446.5359375 : 469,451.5359375 : 451.4609375,420.95 : 532.5546875,420.95 :"
        },
        {
          "name": "verts",
          "xy1": "121.3926329788784,-72.39910556513905 : 186.3926329788784,-74.43035556513905 : 151.3926329788784,-65.36785556513905 : 136.3926329788784,-63.41473056513905 :",
          "xy2": "594,231.5359375 : 659,229.5046875 : 624,238.5671875 : 609,240.5203125 :"
        },
        {
          "name": "verts",
          "xy1": "121.3926329788784,-72.39910556513905 : 111.3926329788784,-74.43035556513905 : 186.3926329788784,-74.43035556513905 :",
          "xy2": "594,231.5359375 : 584,229.5046875 : 659,229.5046875 :"
        },
        {
          "name": "verts",
          "xy1": "71.3926329788784,-57.39910556513905 : 31.392632978878396,-74.43035556513905 : 111.3926329788784,-74.43035556513905 : 76.3926329788784,-58.41473056513905 :",
          "xy2": "544,246.5359375 : 504,229.5046875 : 584,229.5046875 : 549,245.5203125 :"
        },
        {
          "name": "verts",
          "xy1": "131.3926329788784,142.60089443486095 : 11.392632978878396,149.55401943486095 : 1.392632978878396,149.55401943486095 : -3.607367021121604,147.60089443486095 :",
          "xy2": "604,446.5359375 : 484,453.4890625 : 474,453.4890625 : 469,451.5359375 :"
        },
        {
          "name": "verts",
          "xy1": "131.3926329788784,142.60089443486095 : 56.392632978878396,258.616519434861 : 11.392632978878396,149.55401943486095 :",
          "xy2": "604,446.5359375 : 529,562.5515625 : 484,453.4890625 :"
        },
        {
          "name": "verts",
          "xy1": "191.3926329788784,124.63214443486095 : 56.392632978878396,258.616519434861 : 131.3926329788784,142.60089443486095 :",
          "xy2": "664,428.5671875 : 529,562.5515625 : 604,446.5359375 :"
        },
        {
          "name": "verts",
          "xy1": "194.8691954788784,122.01495693486095 : 229.9473204788784,262.014956934861 : 226.3926329788784,264.616519434861 : 61.392632978878396,264.616519434861 : 57.916070478878396,262.014956934861 : 56.392632978878396,258.616519434861 : 191.3926329788784,124.63214443486095 :",
          "xy2": "667.4765625,425.95 : 702.5546875,565.95 : 699,568.5515625 : 534,568.5515625 : 530.5234375,565.95 : 529,562.5515625 : 664,428.5671875 :"
        },
        {
          "name": "verts",
          "xy1": "193.9316954788784,112.01495693486095 : 231.3926329788784,-75.36785556513905 : 229.9473204788784,262.014956934861 : 194.8691954788784,122.01495693486095 :",
          "xy2": "666.5390625,415.95 : 704,228.5671875 : 702.5546875,565.95 : 667.4765625,425.95 :"
        },
        {
          "name": "verts",
          "xy1": "189.9473204788784,-72.98504306513905 : 231.3926329788784,-75.36785556513905 : 193.9316954788784,112.01495693486095 : 176.9004454788784,-17.985043065139052 : 176.9004454788784,-27.985043065139052 :",
          "xy2": "662.5546875,230.95 : 704,228.5671875 : 666.5390625,415.95 : 649.5078125,285.95 : 649.5078125,275.95 :"
        },
        {
          "name": "verts",
          "xy1": "186.3926329788784,-74.43035556513905 : 231.3926329788784,-75.36785556513905 : 189.9473204788784,-72.98504306513905 :",
          "xy2": "659,229.5046875 : 704,228.5671875 : 662.5546875,230.95 :"
        },
        {
          "name": "verts",
          "xy1": "186.3926329788784,-74.43035556513905 : 31.392632978878396,-74.43035556513905 : 231.3926329788784,-75.36785556513905 :",
          "xy2": "659,229.5046875 : 504,229.5046875 : 704,228.5671875 :"
        },
        {
          "name": "verts",
          "xy1": "5.962945478878396,-172.98504306513905 : -33.099554521121604,-137.98504306513905 : -44.037054521121604,-157.98504306513905 : -43.607367021121604,-160.44598056513905 : 1.392632978878396,-177.39910556513905 :",
          "xy2": "478.5703125,130.95 : 439.5078125,165.95 : 428.5703125,145.95 : 429,143.4890625 : 474,126.53593749999999 :"
        },
        {
          "name": "verts",
          "xy1": "31.392632978878396,-74.43035556513905 : 6.392632978878396,-108.41473056513905 : 559.9481017288782,-107.98504306513905 : 560.4606017288783,-77.98504306513905 : 231.3926329788784,-75.36785556513905 :",
          "xy2": "504,229.5046875 : 479,195.5203125 : 1032.5554687499998,195.95 : 1033.0679687499999,225.95 : 704,228.5671875 :"
        },
        {
          "name": "verts",
          "xy1": "-25.130804521121604,-57.98504306513905 : 26.900445478878396,-72.98504306513905 : 6.392632978878396,-43.41473056513905 : 1.392632978878396,-43.41473056513905 :",
          "xy2": "447.4765625,245.95 : 499.5078125,230.95 : 479,260.5203125 : 474,260.5203125 :"
        },
        {
          "name": "verts",
          "xy1": "-25.130804521121604,-117.98504306513905 : 6.392632978878396,-108.41473056513905 : 31.392632978878396,-74.43035556513905 : 26.900445478878396,-72.98504306513905 : -25.130804521121604,-57.98504306513905 :",
          "xy2": "447.4765625,185.95 : 479,195.5203125 : 504,229.5046875 : 499.5078125,230.95 : 447.4765625,245.95 :"
        },
        {
          "name": "verts",
          "xy1": "-25.130804521121604,-117.98504306513905 : -33.099554521121604,-137.98504306513905 : 5.962945478878396,-172.98504306513905 : 6.392632978878396,-108.41473056513905 :",
          "xy2": "447.4765625,185.95 : 439.5078125,165.95 : 478.5703125,130.95 : 479,195.5203125 :"
        },
        {
          "name": "verts",
          "xy1": "-286.0683045211216,-267.98504306513905 : -261.1464295211216,-267.98504306513905 : -261.1464295211216,-242.98504306513905 : -263.6073670211216,-242.39910556513905 : -283.6073670211216,-254.43035556513905 : -286.0683045211216,-257.98504306513905 :",
          "xy2": "186.5390625,35.94999999999999 : 211.4609375,35.94999999999999 : 211.4609375,60.94999999999999 : 209,61.53593749999999 : 189,49.50468749999999 : 186.5390625,45.94999999999999 :"
        },
        {
          "name": "verts",
          "xy1": "-286.0683045211216,-267.98504306513905 : -288.6073670211216,-269.35223056513905 : -258.6073670211216,-269.35223056513905 : -261.1464295211216,-267.98504306513905 :",
          "xy2": "186.5390625,35.94999999999999 : 184,34.58281249999999 : 214,34.58281249999999 : 211.4609375,35.94999999999999 :"
        },
        {
          "name": "verts",
          "xy1": "-183.6073670211216,-269.35223056513905 : -443.6073670211216,-269.35223056513905 : -178.6073670211216,-270.44598056513905 :",
          "xy2": "289,34.58281249999999 : 29,34.58281249999999 : 294,33.48906249999999 :"
        },
        {
          "name": "verts",
          "xy1": "-443.6073670211216,-269.35223056513905 : -473.1776795211216,-302.98504306513905 : -468.6073670211216,-305.44598056513905 : -148.6073670211216,-305.44598056513905 : -145.1308045211216,-302.98504306513905 : -178.6073670211216,-270.44598056513905 :",
          "xy2": "29,34.58281249999999 : -0.5703125,0.9499999999999886 : 4,-1.5109375000000114 : 324,-1.5109375000000114 : 327.4765625,0.9499999999999886 : 294,33.48906249999999 :"
        },
        {
          "name": "verts",
          "xy1": "-448.0214295211216,-267.98504306513905 : -473.1776795211216,-302.98504306513905 : -443.6073670211216,-269.35223056513905 :",
          "xy2": "24.5859375,35.94999999999999 : -0.5703125,0.9499999999999886 : 29,34.58281249999999 :"
        },
        {
          "name": "verts",
          "xy1": "-448.0214295211216,-267.98504306513905 : -448.6073670211216,196.58526943486095 : -468.6073670211216,196.58526943486095 : -473.1776795211216,192.01495693486095 : -473.1776795211216,-302.98504306513905 :",
          "xy2": "24.5859375,35.94999999999999 : 24,500.5203125 : 4,500.5203125 : -0.5703125,495.95 : -0.5703125,0.9499999999999886 :"
        },
        {
          "name": "verts",
          "xy1": "228.8535704788784,-272.98504306513905 : 226.3926329788784,-269.35223056513905 : 191.3926329788784,-269.35223056513905 : 186.3926329788784,-276.46160556513905 : 171.9785704788784,-317.98504306513905 : 176.3926329788784,-319.43035556513905 : 226.3926329788784,-319.43035556513905 : 228.8535704788784,-317.98504306513905 :",
          "xy2": "701.4609375,30.94999999999999 : 699,34.58281249999999 : 664,34.58281249999999 : 659,27.47343749999999 : 644.5859375,-14.050000000000011 : 649,-15.495312500000011 : 699,-15.495312500000011 : 701.4609375,-14.050000000000011 :"
        }
      ]
    }
  }
}